LICENSE
README.md
setup.py
arthorian_quest/__init__.py
arthorian_quest/arthorstein.py
arthorian_quest/create.py
arthorian_quest/ops.py
arthorian_quest/query.py
arthorian_quest/quick_place.py
arthorian_quest/shorthands.py
arthorian_quest.egg-info/PKG-INFO
arthorian_quest.egg-info/SOURCES.txt
arthorian_quest.egg-info/dependency_links.txt
arthorian_quest.egg-info/requires.txt
arthorian_quest.egg-info/top_level.txt